BrainRender
Data
Docs
Examples
Output
User
brainrender
dist
tests
