Metadata-Version: 2.1
Name: brainrender-test
Version: 0.3.3.8rc2
Summary: Python scripts to use Allen Brain Map data for analysis and rendering
Home-page: https://github.com/BrancoLab/brainrender
Author: Federico Claudi
License: UNKNOWN
Platform: UNKNOWN
Requires-Python: >=3.6, <3.8
Provides-Extra: nb
Provides-Extra: dev
